{
  "enablePullDownRefresh": true,
  "navigationBarBackgroundColor": "#3695e3",
  "backgroundColorBottom": "#ffffff",
  "navigationBarTextStyle": "white",
  "usingComponents": {
    "van-icon": "@vant/weapp/icon/index",
    "my-image": "/components/my-image/index",
    "pdt-list": "/components/pdt-list/index",
    "pdt-scroll": "/components/pdt-scroll/index",
    "van-toast": "@vant/weapp/toast/index",
    "van-tag": "@vant/weapp/tag/index",
    "van-popup": "@vant/weapp/popup/index",
    "van-button": "@vant/weapp/button/index"
  }
}